app/demo.py
app/helloWorld.py
app/hello_world.py
AppDemo-0.0.7.dist-info/LICENSE
AppDemo-0.0.7.dist-info/METADATA
AppDemo-0.0.7.dist-info/WHEEL
AppDemo-0.0.7.dist-info/top_level.txt
AppDemo-0.0.7.dist-info/RECORD
