Metadata-Version: 2.1
Name: AppDemo
Version: 0.0.7
Summary: A small example package
License: MIT License
Requires-Python: >=3
License-File: LICENSE
Requires-Dist: streamlit
